[
  {
    "content_id": "tmdb_movie_552524",
    "title": "Lilo & Stitch",
    "platform": "prime_video",
    "genres": [
      "family",
      "science fiction",
      "comedy",
      "adventure"
    ],
    "rating": 7.1,
    "similarity_score": 0.30077041615710115,
    "base_similarity": 0.27763423029886264,
    "temporal_boost": 1.0833333333333333,
    "time_context": "night",
    "reason": "Matches your night preference for family, science fiction"
  },
  {
    "content_id": "tmdb_movie_20760",
    "title": "Lilo & Stitch 2: Stitch Has a Glitch",
    "platform": "hotstar",
    "genres": [
      "animation",
      "family",
      "comedy",
      "science fiction"
    ],
    "rating": 6.7,
    "similarity_score": 0.2821924945790823,
    "base_similarity": 0.25874623390188856,
    "temporal_boost": 1.0906148867313914,
    "time_context": "night",
    "reason": "Matches your night preference for animation, family"
  },
  {
    "content_id": "tmdb_movie_348350",
    "title": "Solo: A Star Wars Story",
    "platform": "hotstar",
    "genres": [
      "science fiction",
      "adventure",
      "action"
    ],
    "rating": 6.6,
    "similarity_score": 0.1558646736289547,
    "base_similarity": 0.14583553111687209,
    "temporal_boost": 1.0687702265372168,
    "time_context": "night",
    "reason": "Matches your night preference for science fiction, adventure"
  },
  {
    "content_id": "tmdb_movie_181812",
    "title": "Star Wars: The Rise of Skywalker",
    "platform": "hotstar",
    "genres": [
      "adventure",
      "action",
      "science fiction"
    ],
    "rating": 6.3,
    "similarity_score": 0.12132811589800942,
    "base_similarity": 0.11352123485990889,
    "temporal_boost": 1.0687702265372168,
    "time_context": "night",
    "reason": "Matches your night preference for adventure, action"
  },
  {
    "content_id": "tmdb_movie_580988",
    "title": "Uma & Haggen",
    "platform": "prime_video",
    "genres": [
      "animation",
      "family",
      "adventure"
    ],
    "rating": 8.8,
    "similarity_score": 0.10154790630062437,
    "base_similarity": 0.09331837337365928,
    "temporal_boost": 1.088187702265372,
    "time_context": "night",
    "reason": "Matches your night preference for animation, family"
  },
  {
    "content_id": "tmdb_movie_482321",
    "title": "Ron's Gone Wrong",
    "platform": "prime_video",
    "genres": [
      "animation",
      "science fiction",
      "family",
      "comedy"
    ],
    "rating": 7.9,
    "similarity_score": 0.09842020612647989,
    "base_similarity": 0.09024285962338958,
    "temporal_boost": 1.0906148867313914,
    "time_context": "night",
    "reason": "Matches your night preference for animation, science fiction"
  },
  {
    "content_id": "tmdb_movie_666154",
    "title": "Kayara",
    "platform": "prime_video",
    "genres": [
      "adventure",
      "animation",
      "family"
    ],
    "rating": 7.7,
    "similarity_score": 0.0963393213915392,
    "base_similarity": 0.08853189683267097,
    "temporal_boost": 1.088187702265372,
    "time_context": "night",
    "reason": "Matches your night preference for adventure, animation"
  },
  {
    "content_id": "tmdb_movie_1184918",
    "title": "The Wild Robot",
    "platform": "hotstar",
    "genres": [
      "animation",
      "science fiction",
      "family"
    ],
    "rating": 8.3,
    "similarity_score": 0.09205434023535378,
    "base_similarity": 0.08459417437241433,
    "temporal_boost": 1.088187702265372,
    "time_context": "night",
    "reason": "Matches your night preference for animation, science fiction"
  },
  {
    "content_id": "tmdb_movie_283995",
    "title": "Guardians of the Galaxy Vol. 2",
    "platform": "netflix",
    "genres": [
      "science fiction",
      "adventure",
      "action"
    ],
    "rating": 7.6,
    "similarity_score": 0.08836474240471243,
    "base_similarity": 0.08267889599714198,
    "temporal_boost": 1.0687702265372168,
    "time_context": "night",
    "reason": "Matches your night preference for science fiction, adventure"
  },
  {
    "content_id": "tmdb_tv_656",
    "title": "Curious George",
    "platform": "hotstar",
    "genres": [
      "animation",
      "family",
      "kids"
    ],
    "rating": 7.1,
    "similarity_score": 0.08595480827247175,
    "base_similarity": 0.08068871622134816,
    "temporal_boost": 1.0652642934196332,
    "time_context": "night",
    "reason": "Matches your night preference for animation, family"
  }
]